{
  "nav": [
    {
      "link": "/home",
      "isIcon": false,
      "isMenu": false,
      "text": "Home"
    },
    {
      "link": "/blog",
      "isIcon": false,
      "isMenu": false,
      "text": "Service"
    },
    {
      "link": "/team",
      "isIcon": false,
      "isMenu": false,
      "text": "Team"
    },
    {
      "link": "/industry",
      "isIcon": false,
      "isMenu": false,
      "text": "industry"
    },
    {
      "link": "/contact",
      "isIcon": false,
      "isMenu": false,
      "text": "Contact"
    }
  ]
}